surfvis/__init__.py
surfvis/flagchi2.py
surfvis/surfchi2.py
surfvis/surfvis.py
surfvis/utils.py
tests/__init__.py
tests/test_trivial.py
surfvis-0.0.1.dist-info/METADATA
surfvis-0.0.1.dist-info/WHEEL
surfvis-0.0.1.dist-info/entry_points.txt
surfvis-0.0.1.dist-info/top_level.txt
surfvis-0.0.1.dist-info/RECORD
