Metadata-Version: 2.1
Name: surfvis
Version: 0.0.1
Summary: Per-baseline time/freq and Chi-Square plots
Home-page: https://github.com/ratt-ru/surfvis
Author: Ian Heywood
Author-email: ianh@astro.ox.ac.uk
Classifier: Programming Language :: Python :: 3
Classifier: License :: OSI Approved :: MIT License
Classifier: Operating System :: OS Independent
Requires-Python: >=3.7
Requires-Dist: matplotlib
Requires-Dist: python-casacore
Requires-Dist: argparse
Requires-Dist: ipython
Requires-Dist: codex-africanus[dask]
Requires-Dist: astropy
Requires-Dist: scipy
Requires-Dist: dask-ms[xarray,zarr]
Requires-Dist: pytest (>=6.2.2)
